stlitepack/__init__.py
stlitepack/pack.py
stlitepack/publish.py
stlitepack-0.4.5.dist-info/METADATA
stlitepack-0.4.5.dist-info/WHEEL
stlitepack-0.4.5.dist-info/licenses/LICENCE.md
stlitepack-0.4.5.dist-info/RECORD
