Metadata-Version: 2.4
Name: stlitepack
Version: 0.4.5
Summary: A package for converting streamlit apps to stlite apps to remove the need for hosting
Project-URL: Homepage, https://github.com/Bergam0t/stlitepack
Project-URL: Bug Tracker, https://github.com/Bergam0t/stlitepack/issues
Author-email: Sammi Rosser <s.j.rosser@exeter.ac.uk>
License-Expression: Apache-2.0
License-File: LICENCE.md
Classifier: License :: OSI Approved :: Apache Software License
Classifier: Operating System :: OS Independent
Classifier: Programming Language :: Python :: 3.9
Classifier: Programming Language :: Python :: 3.10
Classifier: Programming Language :: Python :: 3.11
Classifier: Programming Language :: Python :: 3.12
Requires-Python: >=3.9
Requires-Dist: packaging>=21.0
Requires-Dist: requests<3.0,>=2.22.0
